translatesrt/__init__.py
translatesrt-0.0.4.dist-info/METADATA
translatesrt-0.0.4.dist-info/WHEEL
translatesrt-0.0.4.dist-info/entry_points.txt
translatesrt-0.0.4.dist-info/top_level.txt
translatesrt-0.0.4.dist-info/RECORD
