Metadata-Version: 2.1
Name: translatesrt
Version: 0.0.4
Summary: a utility for translating a subtitle file to another language
Home-page: https://github.com/botbahlul/translatesrt
Author: Bot Bahlul
Author-email: bot.bahlul@gmail.com
License: MIT License
Requires-Dist: pysrt >=1.0.1
Requires-Dist: progressbar2 >=3.34.3
